MyCatApi/__init__.py
MyCatApi/api.py
mycatapi-0.1.dist-info/METADATA
mycatapi-0.1.dist-info/WHEEL
mycatapi-0.1.dist-info/top_level.txt
mycatapi-0.1.dist-info/RECORD
