Metadata-Version: 2.4
Name: MyCatApi
Version: 0.1
Summary: API для работы с фактами о котах
Author: Твоё имя
Requires-Python: >=3.6
Requires-Dist: requests
Dynamic: author
Dynamic: description
Dynamic: description-content-type
Dynamic: requires-dist
Dynamic: requires-python
Dynamic: summary
